shortcut/__init__.py
shortcut/base.py
shortcut/exception.py
shortcut/linux.py
shortcut/macos.py
shortcut/windows.py
shortcut-0.0.2.dist-info/DESCRIPTION.rst
shortcut-0.0.2.dist-info/METADATA
shortcut-0.0.2.dist-info/RECORD
shortcut-0.0.2.dist-info/WHEEL
shortcut-0.0.2.dist-info/entry_points.txt
shortcut-0.0.2.dist-info/metadata.json
shortcut-0.0.2.dist-info/top_level.txt
