Metadata-Version: 2.0
Name: shortcut
Version: 0.0.2
Summary: A X platform super simple api and command line application for creating shortcuts
Home-page: https://github.com/martinohanlon/shortcut
Author: Martin O'Hanlon
Author-email: martin@ohanlonweb.com
License: MIT
Platform: UNKNOWN
Requires-Dist: pypiwin32; sys_platform == "win32"
Requires-Dist: winshell; sys_platform == "win32"
